{
    "Version": "1.2",
    "Data": {
        "Source": "c:\\dev\\gamedev\\epic\\acd\\acd\\intermediate\\build\\win64\\unrealeditor\\inc\\acd\\uht\\acdprojectile.gen.cpp",
        "ProvidedModule": "",
        "PCH": "c:\\dev\\gamedev\\epic\\acd\\acd\\intermediate\\build\\win64\\x64\\acdeditor\\development\\unrealed\\sharedpch.unrealed.project.valapi.cpp20.h.pch",
        "Includes": [
            "c:\\dev\\gamedev\\epic\\acd\\acd\\intermediate\\build\\win64\\x64\\unrealeditor\\development\\acd\\definitions.acd.h",
            "c:\\dev\\gamedev\\epic\\acd\\acd\\source\\acd\\acdprojectile.h",
            "c:\\dev\\gamedev\\epic\\acd\\acd\\intermediate\\build\\win64\\unrealeditor\\inc\\acd\\uht\\acdprojectile.generated.h"
        ],
        "ImportedModules": [],
        "ImportedHeaderUnits": []
    }
}